sql_on_csv/__init__.py
sql_on_csv-0.0.8.dist-info/METADATA
sql_on_csv-0.0.8.dist-info/WHEEL
sql_on_csv-0.0.8.dist-info/top_level.txt
sql_on_csv-0.0.8.dist-info/RECORD
