Metadata-Version: 2.1
Name: sql-on-csv
Version: 0.0.8
Author: whohow20094702
Author-email: whohow20094702@icloud.com
License: MIT
Classifier: Programming Language :: Python :: 3
Classifier: License :: OSI Approved :: MIT License
Classifier: Operating System :: OS Independent
Requires-Dist: pandas >=2.1.3
Requires-Dist: pandasql >=0.7.3
Requires-Dist: tabulate >=0.9.0
